tinydng_ext.cpython-312-darwin.so
python/tinydng/_version.py
python/tinydng/__init__.py
tinydng-0.1.0.dist-info/RECORD
tinydng-0.1.0.dist-info/LICENSE
tinydng-0.1.0.dist-info/WHEEL
tinydng-0.1.0.dist-info/entry_points.txt
tinydng-0.1.0.dist-info/top_level.txt
tinydng-0.1.0.dist-info/METADATA
