Metadata-Version: 2.1
Name: tinydng
Version: 0.1.0
Summary: Python binding for TinyDNG
Home-page: https://github.com/syoyo/tinydng
Author-email: Syoyo Fujita <syoyo@lighttransport.com>
License-File: LICENSE
